README.md
setup.cfg
setup.py
calendario_bananero/__init__.py
calendario_bananero/calendario_bananero.py
calendario_bananero.egg-info/PKG-INFO
calendario_bananero.egg-info/SOURCES.txt
calendario_bananero.egg-info/dependency_links.txt
calendario_bananero.egg-info/requires.txt
calendario_bananero.egg-info/top_level.txt