Metadata-Version: 2.1
Name: calendario-bananero
Version: 1.1.4
Summary: UNKNOWN
Home-page: https://github.com/PinkFLoyd92/date_helper
Author: Sebastian Caceres
Author-email: chevass@protonmail.com
License: UNKNOWN
Platform: UNKNOWN
Classifier: Programming Language :: Python :: 3
Classifier: License :: OSI Approved :: MIT License
Classifier: Operating System :: OS Independent
Requires-Python: >=3.6
